menusys/__init__.py
menusys/menusys.py
menusys/version.py
menusys-1.1.9.dist-info/LICENSE
menusys-1.1.9.dist-info/METADATA
menusys-1.1.9.dist-info/WHEEL
menusys-1.1.9.dist-info/top_level.txt
menusys-1.1.9.dist-info/RECORD
