Metadata-Version: 2.1
Name: menusys
Version: 1.1.9
Summary: Menu system to easily create a menu in CLI
Home-page: https://menusys.readthedocs.io
Author: Benjamin P. Trachtenberg
Author-email: e_ben_75-python@yahoo.com
License: The MIT License (MIT)
Project-URL: Documentation, https://menusys.readthedocs.io/en/latest/
Project-URL: Source, https://github.com/btr1975/menusys
Project-URL: Tracker, https://github.com/btr1975/menusys/issues
Keywords: menu cli easy helper dictionary
Platform: UNKNOWN
Classifier: Development Status :: 5 - Production/Stable
Classifier: License :: OSI Approved :: MIT License
Classifier: Intended Audience :: Developers
Classifier: Natural Language :: English
Classifier: Operating System :: MacOS :: MacOS X
Classifier: Operating System :: POSIX
Classifier: Operating System :: POSIX :: BSD
Classifier: Operating System :: POSIX :: Linux
Classifier: Operating System :: Microsoft :: Windows
Classifier: Programming Language :: Python :: 3
Classifier: Programming Language :: Python :: 3 :: Only
Classifier: Programming Language :: Python :: 3.6
Classifier: Programming Language :: Python :: 3.7
Classifier: Programming Language :: Python :: 3.8
Requires-Python: >=3.5
License-File: LICENSE
